pylox/__init__.py
pylox/__main__.py
pylox/environment.py
pylox/errors.py
pylox/interpreter.py
pylox/lexer.py
pylox/lox_types.py
pylox/nodes.py
pylox/parser.py
pylox/resolver.py
pylox/tokens.py
pylox/visitor.py
pylox/utils/__init__.py
pylox/utils/ast_printer.py
mypylox-1.2.0.dist-info/LICENSE
mypylox-1.2.0.dist-info/METADATA
mypylox-1.2.0.dist-info/WHEEL
mypylox-1.2.0.dist-info/entry_points.txt
mypylox-1.2.0.dist-info/top_level.txt
mypylox-1.2.0.dist-info/RECORD
