Metadata-Version: 2.1
Name: mypylox
Version: 1.2.0
Summary: A Lox implementation written in Python.
Home-page: https://github.com/tusharsadhwani/pylox
Author: Tushar Sadhwani
Author-email: tushar.sadhwani000@gmail.com
License: MIT
Platform: UNKNOWN
Classifier: License :: OSI Approved :: MIT License
Classifier: Operating System :: OS Independent
Classifier: Programming Language :: Python :: 3
Classifier: Programming Language :: Python :: 3 :: Only
Classifier: Programming Language :: Python :: 3.7
Classifier: Programming Language :: Python :: 3.8
Classifier: Programming Language :: Python :: 3.9
Classifier: Programming Language :: Python :: 3.10
Classifier: Programming Language :: Python :: Implementation :: CPython
Classifier: Typing :: Typed
Requires-Python: >=3.7
License-File: LICENSE
Requires-Dist: attrs (>=21.4.0)
Provides-Extra: dev
Requires-Dist: black ; extra == 'dev'
Requires-Dist: mypy ; extra == 'dev'
Requires-Dist: pytest ; extra == 'dev'
Requires-Dist: pytest-cov ; extra == 'dev'
Requires-Dist: tox ; extra == 'dev'
